bert4tf/__init__.py
bert4tf/attention.py
bert4tf/embeddings.py
bert4tf/extract_features.py
bert4tf/layer.py
bert4tf/load_albert.py
bert4tf/loader_bert.py
bert4tf/loader_roberta.py
bert4tf/model.py
bert4tf/modeling.py
bert4tf/optimization.py
bert4tf/tf_metrics.py
bert4tf/transformer.py
bert4tf/version.py
bert4tf-2.0.2.dist-info/METADATA
bert4tf-2.0.2.dist-info/WHEEL
bert4tf-2.0.2.dist-info/top_level.txt
bert4tf-2.0.2.dist-info/RECORD
