Metadata-Version: 2.1
Name: bert4tf
Version: 2.0.2
Summary: bert for tensorflow2
Home-page: https://github.com/charlesXu86/Bert4tf
Author: xu
Author-email: charlesxu86@163.com
License: MIT Licence
Keywords: bert4tf,tensorflow2
Platform: any
Classifier: Programming Language :: Python :: 3.7
Classifier: Programming Language :: Python :: 3.6
Requires-Dist: tensorflow
